<?xml version="1.0" encoding="utf-8"?>

<?xml-stylesheet type="text/xsl" href="sort-ex2.xsl"?>

<classe>
<étudiants>

 <étudiant>
  <id>299</id>
  <prénom>Ginette</prénom>
  <nom>Ringard</nom>
 </étudiant>

 <étudiant>
  <id>21</id>
  <nom>Plique</nom>
  <prénom>Elsa</prénom>
 </étudiant>

 <étudiant>
  <id>1199</id>
  <prénom>Jules</prénom>
  <nom>Dechez</nom>
 </étudiant>

 <étudiant>
  <id>087</id>
  <prénom>Jeanne</prénom>
  <nom>Doe</nom>
 </étudiant>

 <étudiant>
  <id>156</id>
  <prénom>Jean</prénom>
  <nom>Aymard</nom>
 </étudiant>

 <étudiant>
  <id>100</id>
  <prénom>Jérôme</prénom>
  <nom>Gourdin</nom>
 </étudiant>

 <étudiant>
  <id>22</id>
  <nom>Liguili</nom>
  <prénom>Guy</prénom>
 </étudiant>

 <étudiant>
  <id>69</id>
  <nom>Deubaze</nom>
  <prénom>Raymond</prénom>
 </étudiant>

 <étudiant>
  <id>456</id>
  <prénom>Antoine</prénom>
  <nom>Nette</nom>
 </étudiant>

 <étudiant>
  <id>664</id>
  <nom>Trau</nom>
  <prénom>Julie</prénom>
 </étudiant>

 <étudiant>
  <id>404</id>
  <nom>Duciel</nom>
  <prénom>Sandra</prénom>
 </étudiant>

</étudiants>
</classe>
